{"remainingRequest":"/home/anthony/git_workspaces/kibana/node_modules/thread-loader/dist/cjs.js??ref--9-1!/home/anthony/git_workspaces/kibana/node_modules/babel-loader/lib/index.js??ref--9-2!/home/anthony/git_workspaces/kibana/x-pack/plugins/canvas/public/functions/to.js","dependencies":[{"path":"/home/anthony/git_workspaces/kibana/x-pack/plugins/canvas/public/functions/to.js","mtime":1567631711931},{"path":"/home/anthony/git_workspaces/kibana/node_modules/cache-loader/dist/cjs.js","mtime":1567666236302},{"path":"/home/anthony/git_workspaces/kibana/node_modules/thread-loader/dist/cjs.js","mtime":1567666239443},{"path":"/home/anthony/git_workspaces/kibana/node_modules/babel-loader/lib/index.js","mtime":1567666227676}],"contextDependencies":[],"result":["'use strict';\n\nObject.defineProperty(exports, \"__esModule\", {\n  value: true\n});\nexports.to = undefined;\n\nvar _common = require('@kbn/interpreter/common');\n\nvar _public = require('@kbn/interpreter/public');\n\n/*\n * Copyright Elasticsearch B.V. and/or licensed to Elasticsearch B.V. under one\n * or more contributor license agreements. Licensed under the Elastic License;\n * you may not use this file except in compliance with the Elastic License.\n */\n\nvar to = exports.to = function to() {\n  return {\n    name: 'to',\n    aliases: [],\n    help: 'Explicitly cast from one type to another',\n    context: {},\n    args: {\n      type: {\n        types: ['string'],\n        help: 'A known type',\n        aliases: ['_'],\n        multi: true\n      }\n    },\n    fn: function fn(context, args) {\n      if (!args.type) {\n        throw new Error('Must specify a casting type');\n      }\n\n      return (0, _common.castProvider)(_public.registries.types.toJS())(context, args.type);\n    }\n  };\n};",null]}