{"remainingRequest":"/home/anthony/git_workspaces/kibana/node_modules/thread-loader/dist/cjs.js??ref--9-1!/home/anthony/git_workspaces/kibana/node_modules/babel-loader/lib/index.js??ref--9-2!/home/anthony/git_workspaces/kibana/x-pack/plugins/logstash/common/constants/index.js","dependencies":[{"path":"/home/anthony/git_workspaces/kibana/x-pack/plugins/logstash/common/constants/index.js","mtime":1567631712004},{"path":"/home/anthony/git_workspaces/kibana/node_modules/cache-loader/dist/cjs.js","mtime":1567666236302},{"path":"/home/anthony/git_workspaces/kibana/node_modules/thread-loader/dist/cjs.js","mtime":1567666239443},{"path":"/home/anthony/git_workspaces/kibana/node_modules/babel-loader/lib/index.js","mtime":1567666227676}],"contextDependencies":[],"result":["'use strict';\n\nObject.defineProperty(exports, \"__esModule\", {\n  value: true\n});\n\nvar _index_names = require('./index_names');\n\nObject.defineProperty(exports, 'INDEX_NAMES', {\n  enumerable: true,\n  get: function get() {\n    return _index_names.INDEX_NAMES;\n  }\n});\n\nvar _type_names = require('./type_names');\n\nObject.defineProperty(exports, 'TYPE_NAMES', {\n  enumerable: true,\n  get: function get() {\n    return _type_names.TYPE_NAMES;\n  }\n});\n\nvar _routes = require('./routes');\n\nObject.defineProperty(exports, 'ROUTES', {\n  enumerable: true,\n  get: function get() {\n    return _routes.ROUTES;\n  }\n});\n\nvar _pagination = require('./pagination');\n\nObject.defineProperty(exports, 'PAGINATION', {\n  enumerable: true,\n  get: function get() {\n    return _pagination.PAGINATION;\n  }\n});\n\nvar _plugin = require('./plugin');\n\nObject.defineProperty(exports, 'PLUGIN', {\n  enumerable: true,\n  get: function get() {\n    return _plugin.PLUGIN;\n  }\n});\n\nvar _es_scroll_settings = require('./es_scroll_settings');\n\nObject.defineProperty(exports, 'ES_SCROLL_SETTINGS', {\n  enumerable: true,\n  get: function get() {\n    return _es_scroll_settings.ES_SCROLL_SETTINGS;\n  }\n});\n\nvar _tooltips = require('./tooltips');\n\nObject.defineProperty(exports, 'TOOLTIPS', {\n  enumerable: true,\n  get: function get() {\n    return _tooltips.TOOLTIPS;\n  }\n});\n\nvar _pipeline = require('./pipeline');\n\nObject.defineProperty(exports, 'PIPELINE', {\n  enumerable: true,\n  get: function get() {\n    return _pipeline.PIPELINE;\n  }\n});\n\nvar _monitoring = require('./monitoring');\n\nObject.defineProperty(exports, 'MONITORING', {\n  enumerable: true,\n  get: function get() {\n    return _monitoring.MONITORING;\n  }\n});",null]}