{"remainingRequest":"/home/anthony/git_workspaces/kibana/node_modules/thread-loader/dist/cjs.js??ref--9-1!/home/anthony/git_workspaces/kibana/node_modules/babel-loader/lib/index.js??ref--9-2!/home/anthony/git_workspaces/kibana/src/legacy/core_plugins/inspector_views/public/requests/requests_view.js","dependencies":[{"path":"/home/anthony/git_workspaces/kibana/src/legacy/core_plugins/inspector_views/public/requests/requests_view.js","mtime":1567631711534},{"path":"/home/anthony/git_workspaces/kibana/node_modules/cache-loader/dist/cjs.js","mtime":1567666236302},{"path":"/home/anthony/git_workspaces/kibana/node_modules/thread-loader/dist/cjs.js","mtime":1567666239443},{"path":"/home/anthony/git_workspaces/kibana/node_modules/babel-loader/lib/index.js","mtime":1567666227676}],"contextDependencies":[],"result":["'use strict';\n\nObject.defineProperty(exports, \"__esModule\", {\n  value: true\n});\nexports.RequestsView = undefined;\n\nvar _createClass = function () { function defineProperties(target, props) { for (var i = 0; i < props.length; i++) { var descriptor = props[i]; descriptor.enumerable = descriptor.enumerable || false; descriptor.configurable = true; if (\"value\" in descriptor) descriptor.writable = true; Object.defineProperty(target, descriptor.key, descriptor); } } return function (Constructor, protoProps, staticProps) { if (protoProps) defineProperties(Constructor.prototype, protoProps); if (staticProps) defineProperties(Constructor, staticProps); return Constructor; }; }();\n\nvar _react = require('react');\n\nvar _react2 = _interopRequireDefault(_react);\n\nvar _propTypes = require('prop-types');\n\nvar _propTypes2 = _interopRequireDefault(_propTypes);\n\nvar _eui = require('@elastic/eui');\n\nvar _inspector = require('ui/inspector');\n\nvar _adapters = require('ui/inspector/adapters');\n\nvar _request_selector = require('./request_selector');\n\nvar _request_details = require('./request_details');\n\nvar _react3 = require('@kbn/i18n/react');\n\nvar _i18n = require('@kbn/i18n');\n\nfunction _interopRequireDefault(obj) { return obj && obj.__esModule ? obj : { default: obj }; }\n\nfunction _classCallCheck(instance, Constructor) { if (!(instance instanceof Constructor)) { throw new TypeError(\"Cannot call a class as a function\"); } }\n\nfunction _possibleConstructorReturn(self, call) { if (!self) { throw new ReferenceError(\"this hasn't been initialised - super() hasn't been called\"); } return call && (typeof call === \"object\" || typeof call === \"function\") ? call : self; }\n\nfunction _inherits(subClass, superClass) { if (typeof superClass !== \"function\" && superClass !== null) { throw new TypeError(\"Super expression must either be null or a function, not \" + typeof superClass); } subClass.prototype = Object.create(superClass && superClass.prototype, { constructor: { value: subClass, enumerable: false, writable: true, configurable: true } }); if (superClass) Object.setPrototypeOf ? Object.setPrototypeOf(subClass, superClass) : subClass.__proto__ = superClass; } /*\n                                                                                                                                                                                                                                                                                                                                                                                                                                                                                                                * Licensed to Elasticsearch B.V. under one or more contributor\n                                                                                                                                                                                                                                                                                                                                                                                                                                                                                                                * license agreements. See the NOTICE file distributed with\n                                                                                                                                                                                                                                                                                                                                                                                                                                                                                                                * this work for additional information regarding copyright\n                                                                                                                                                                                                                                                                                                                                                                                                                                                                                                                * ownership. Elasticsearch B.V. licenses this file to you under\n                                                                                                                                                                                                                                                                                                                                                                                                                                                                                                                * the Apache License, Version 2.0 (the \"License\"); you may\n                                                                                                                                                                                                                                                                                                                                                                                                                                                                                                                * not use this file except in compliance with the License.\n                                                                                                                                                                                                                                                                                                                                                                                                                                                                                                                * You may obtain a copy of the License at\n                                                                                                                                                                                                                                                                                                                                                                                                                                                                                                                *\n                                                                                                                                                                                                                                                                                                                                                                                                                                                                                                                *    http://www.apache.org/licenses/LICENSE-2.0\n                                                                                                                                                                                                                                                                                                                                                                                                                                                                                                                *\n                                                                                                                                                                                                                                                                                                                                                                                                                                                                                                                * Unless required by applicable law or agreed to in writing,\n                                                                                                                                                                                                                                                                                                                                                                                                                                                                                                                * software distributed under the License is distributed on an\n                                                                                                                                                                                                                                                                                                                                                                                                                                                                                                                * \"AS IS\" BASIS, WITHOUT WARRANTIES OR CONDITIONS OF ANY\n                                                                                                                                                                                                                                                                                                                                                                                                                                                                                                                * KIND, either express or implied.  See the License for the\n                                                                                                                                                                                                                                                                                                                                                                                                                                                                                                                * specific language governing permissions and limitations\n                                                                                                                                                                                                                                                                                                                                                                                                                                                                                                                * under the License.\n                                                                                                                                                                                                                                                                                                                                                                                                                                                                                                                */\n\nvar RequestsViewComponent = function (_Component) {\n  _inherits(RequestsViewComponent, _Component);\n\n  function RequestsViewComponent(props) {\n    _classCallCheck(this, RequestsViewComponent);\n\n    var _this = _possibleConstructorReturn(this, (RequestsViewComponent.__proto__ || Object.getPrototypeOf(RequestsViewComponent)).call(this, props));\n\n    _initialiseProps.call(_this);\n\n    props.adapters.requests.on('change', _this._onRequestsChange);\n\n    var requests = props.adapters.requests.getRequests();\n    _this.state = {\n      requests: requests,\n      request: requests.length ? requests[0] : null\n    };\n    return _this;\n  }\n\n  _createClass(RequestsViewComponent, [{\n    key: 'componentWillUnmount',\n    value: function componentWillUnmount() {\n      this.props.adapters.requests.removeListener('change', this._onRequestsChange);\n    }\n  }, {\n    key: 'renderEmptyRequests',\n    value: function renderEmptyRequests() {\n      return _react2.default.createElement(\n        _inspector.InspectorView,\n        { useFlex: true },\n        _react2.default.createElement(_eui.EuiEmptyPrompt, {\n          'data-test-subj': 'inspectorNoRequestsMessage',\n          title: _react2.default.createElement(\n            'h2',\n            null,\n            _react2.default.createElement(_react3.FormattedMessage, {\n              id: 'inspectorViews.requests.noRequestsLoggedTitle',\n              defaultMessage: 'No requests logged'\n            })\n          ),\n          body: _react2.default.createElement(\n            _react2.default.Fragment,\n            null,\n            _react2.default.createElement(\n              'p',\n              null,\n              _react2.default.createElement(_react3.FormattedMessage, {\n                id: 'inspectorViews.requests.noRequestsLoggedDescription.elementHasNotLoggedAnyRequestsText',\n                defaultMessage: 'The element hasn\\'t logged any requests (yet).'\n              })\n            ),\n            _react2.default.createElement(\n              'p',\n              null,\n              _react2.default.createElement(_react3.FormattedMessage, {\n                id: 'inspectorViews.requests.noRequestsLoggedDescription.whatDoesItUsuallyMeanText',\n                defaultMessage: 'This usually means that there was no need to fetch any data or that the element has not yet started fetching data.'\n              })\n            )\n          )\n        })\n      );\n    }\n  }, {\n    key: 'render',\n    value: function render() {\n      if (!this.state.requests || !this.state.requests.length) {\n        return this.renderEmptyRequests();\n      }\n\n      var failedCount = this.state.requests.filter(function (req) {\n        return req.status === _adapters.RequestStatus.ERROR;\n      }).length;\n\n      return _react2.default.createElement(\n        _inspector.InspectorView,\n        null,\n        _react2.default.createElement(\n          _eui.EuiText,\n          { size: 'xs' },\n          _react2.default.createElement(\n            'p',\n            { role: 'status', 'aria-live': 'polite', 'aria-atomic': 'true' },\n            _react2.default.createElement(_react3.FormattedMessage, {\n              id: 'inspectorViews.requests.requestWasMadeDescription',\n              defaultMessage: '{requestsCount, plural, one {# request was} other {# requests were} } made{failedRequests}',\n              values: {\n                requestsCount: this.state.requests.length,\n                failedRequests: failedCount > 0 ? _react2.default.createElement(\n                  _eui.EuiTextColor,\n                  { color: 'danger' },\n                  _react2.default.createElement(_react3.FormattedMessage, {\n                    id: 'inspectorViews.requests.requestWasMadeDescription.requestHadFailureText',\n                    defaultMessage: ', {failedCount} had a failure',\n                    values: { failedCount: failedCount }\n                  })\n                ) : ''\n              }\n            })\n          )\n        ),\n        _react2.default.createElement(_eui.EuiSpacer, { size: 'xs' }),\n        _react2.default.createElement(_request_selector.RequestSelector, {\n          requests: this.state.requests,\n          selectedRequest: this.state.request,\n          onRequestChanged: this.selectRequest\n        }),\n        _react2.default.createElement(_eui.EuiSpacer, { size: 'xs' }),\n        this.state.request && this.state.request.description && _react2.default.createElement(\n          _eui.EuiText,\n          { size: 'xs' },\n          _react2.default.createElement(\n            'p',\n            null,\n            this.state.request.description\n          )\n        ),\n        _react2.default.createElement(_eui.EuiSpacer, { size: 'm' }),\n        this.state.request && _react2.default.createElement(_request_details.RequestDetails, {\n          request: this.state.request\n        })\n      );\n    }\n  }]);\n\n  return RequestsViewComponent;\n}(_react.Component);\n\nvar _initialiseProps = function _initialiseProps() {\n  var _this2 = this;\n\n  this._onRequestsChange = function () {\n    var requests = _this2.props.adapters.requests.getRequests();\n    var newState = { requests: requests };\n    if (!requests.includes(_this2.state.request)) {\n      newState.request = requests.length ? requests[0] : null;\n    }\n    _this2.setState(newState);\n  };\n\n  this.selectRequest = function (request) {\n    if (request !== _this2.state.request) {\n      _this2.setState({ request: request });\n    }\n  };\n};\n\nRequestsViewComponent.propTypes = {\n  adapters: _propTypes2.default.object.isRequired\n};\n\nvar RequestsView = {\n  title: _i18n.i18n.translate('inspectorViews.requests.requestsTitle', {\n    defaultMessage: 'Requests'\n  }),\n  order: 20,\n  help: _i18n.i18n.translate('inspectorViews.requests.requestsDescriptionTooltip', {\n    defaultMessage: 'View the requests that collected the data'\n  }),\n  shouldShow: function shouldShow(adapters) {\n    return Boolean(adapters.requests);\n  },\n\n  component: RequestsViewComponent\n};\n\nexports.RequestsView = RequestsView;",null]}