{"remainingRequest":"/home/anthony/git_workspaces/kibana/node_modules/thread-loader/dist/cjs.js??ref--9-1!/home/anthony/git_workspaces/kibana/node_modules/babel-loader/lib/index.js??ref--9-2!/home/anthony/git_workspaces/kibana/x-pack/plugins/canvas/canvas_plugin_src/uis/datasources/demodata.js","dependencies":[{"path":"/home/anthony/git_workspaces/kibana/x-pack/plugins/canvas/canvas_plugin_src/uis/datasources/demodata.js","mtime":1567631711910},{"path":"/home/anthony/git_workspaces/kibana/node_modules/cache-loader/dist/cjs.js","mtime":1567666236302},{"path":"/home/anthony/git_workspaces/kibana/node_modules/thread-loader/dist/cjs.js","mtime":1567666239443},{"path":"/home/anthony/git_workspaces/kibana/node_modules/babel-loader/lib/index.js","mtime":1567666227676}],"contextDependencies":[],"result":["'use strict';\n\nObject.defineProperty(exports, \"__esModule\", {\n  value: true\n});\nexports.demodata = undefined;\n\nvar _react = require('react');\n\nvar _react2 = _interopRequireDefault(_react);\n\nvar _eui = require('@elastic/eui');\n\nvar _template_from_react_component = require('../../../public/lib/template_from_react_component');\n\nfunction _interopRequireDefault(obj) { return obj && obj.__esModule ? obj : { default: obj }; }\n\nvar DemodataDatasource = function DemodataDatasource() {\n  return _react2.default.createElement(\n    _eui.EuiText,\n    null,\n    _react2.default.createElement(\n      'h3',\n      null,\n      'You are using demo data'\n    ),\n    _react2.default.createElement(\n      'p',\n      null,\n      'This data source is connected to every Canvas element by default. Its purpose is to give you some playground data to get started. The demo set contains 4 strings, 3 numbers and a date. Feel free to experiment and, when you\\'re ready, click ',\n      _react2.default.createElement(\n        'strong',\n        null,\n        'Change your data source'\n      ),\n      ' ',\n      'above to connect to your own data.'\n    )\n  );\n}; /*\n    * Copyright Elasticsearch B.V. and/or licensed to Elasticsearch B.V. under one\n    * or more contributor license agreements. Licensed under the Elastic License;\n    * you may not use this file except in compliance with the Elastic License.\n    */\n\nvar demodata = exports.demodata = function demodata() {\n  return {\n    name: 'demodata',\n    displayName: 'Demo data',\n    help: 'Mock data set with usernames, prices, projects, countries, and phases',\n    // Replace this with a better icon when we have time.\n    image: 'logoElasticStack',\n    template: (0, _template_from_react_component.templateFromReactComponent)(DemodataDatasource)\n  };\n};",null]}